{"assets":{"C12B6BF5A5E74E88C4963D707DCDDFDD":{"type":"texture","index":1,"url":{"native":"assets\/E4407243-C40A-4E3B-9621-4F902075C3D4.pdf"},"width":2168,"height":1094},"3EDDAE3FDD7A654053D0AEA069F8D648":{"type":"texture","index":11,"url":{"native":"assets\/E4407243-C40A-4E3B-9621-4F902075C3D4.pdf"},"width":1920,"height":1080},"B2F0BCA7C2A8885167BA19674E52A20A":{"type":"texture","index":10,"url":{"native":"assets\/E4407243-C40A-4E3B-9621-4F902075C3D4.pdf"},"width":209,"height":90},"11A3D575BC6A00BAD4CC17A5FF6DDE99":{"type":"texture","index":12,"url":{"native":"assets\/E4407243-C40A-4E3B-9621-4F902075C3D4.pdf"},"width":1920,"height":1080},"5FF86E2A824437EFAD54AE3258E09603":{"type":"texture","index":9,"url":{"native":"assets\/E4407243-C40A-4E3B-9621-4F902075C3D4.pdf"},"width":103,"height":103},"C25C25FF361FB24FC35F6B120D2F252D":{"type":"texture","index":0,"url":{"native":"assets\/E4407243-C40A-4E3B-9621-4F902075C3D4.pdf"},"width":1920,"height":1080},"1C2D85C57D1BBC48B0C74B45B529F370":{"type":"texture","index":8,"url":{"native":"assets\/E4407243-C40A-4E3B-9621-4F902075C3D4.pdf"},"width":76,"height":341},"EFF3C19DC1DDB806575AEFA5F6781351":{"type":"texture","index":3,"url":{"native":"assets\/E4407243-C40A-4E3B-9621-4F902075C3D4.pdf"},"width":686,"height":770},"B28C276801367825A84224717157A0E8":{"type":"texture","index":7,"url":{"native":"assets\/E4407243-C40A-4E3B-9621-4F902075C3D4.pdf"},"width":482,"height":425},"C3D1CCE3C5DB939E97237F1C22DA967F":{"type":"texture","index":5,"url":{"native":"assets\/E4407243-C40A-4E3B-9621-4F902075C3D4.pdf"},"width":929,"height":146},"D21B500D2A0739DD8D73AF590CB61ADB":{"type":"texture","index":2,"url":{"native":"assets\/E4407243-C40A-4E3B-9621-4F902075C3D4.pdf"},"width":143,"height":71},"24BF7CAAC7FD459582A8B21E36FC6381":{"type":"texture","index":6,"url":{"native":"assets\/E4407243-C40A-4E3B-9621-4F902075C3D4.pdf"},"width":386,"height":58},"8476563D8982227EF9FBEC92502EAADE":{"type":"texture","index":4,"url":{"native":"assets\/E4407243-C40A-4E3B-9621-4F902075C3D4.pdf"},"width":114,"height":44},"1AC1D9AB0AA6A4AF2C78CE39642C3533":{"type":"texture","index":13,"url":{"native":"assets\/E4407243-C40A-4E3B-9621-4F902075C3D4.pdf"},"width":1920,"height":1080}},"events":[{"effects":[{"beginTime":0,"baseLayer":{"animations":[],"initialState":{"affineTransform":[1,0,0,1,0,0],"masksToBounds":false,"rotation":0,"scale":1,"position":{"pointX":837.51203266779544,"pointY":79.999996344248459},"width":929,"sublayerTransform":[1,0,0,0,0,1,0,0,0,0,1,0,0,0,0,1],"contentsRect":{"y":0,"x":0,"width":1,"height":1},"opacity":1,"edgeAntialiasingMask":251658240,"height":146,"hidden":false,"anchorPoint":{"pointX":0.5,"pointY":0.5}},"objectID":"AB6BDAF9-BBF8-4D6D-9832-43AEF85F30BD","layers":[{"animations":[],"initialState":{"affineTransform":[1,0,0,1,0,0],"masksToBounds":false,"rotation":0,"scale":1,"position":{"pointX":586.98796733220456,"pointY":533.00000365575158},"width":929,"sublayerTransform":[1,0,0,0,0,1,0,0,0,0,1,-0.00035007912466775983,0,0,0,1],"contentsRect":{"y":0,"x":0,"width":1,"height":1},"opacity":1,"edgeAntialiasingMask":251658240,"height":146,"hidden":false,"anchorPoint":{"pointX":0.63184926515845485,"pointY":3.6506849565462436}},"layers":[{"animations":[{"additive":false,"timeOffset":0,"beginTime":1e-100,"repeatCount":0,"fillMode":"both","duration":0.75,"autoreverses":false,"animations":[{"additive":false,"timeOffset":0,"beginTime":0,"from":{"scalar":false},"repeatCount":0,"fillMode":"forwards","duration":0.75,"autoreverses":false,"property":"hidden","to":{"scalar":false},"removedOnCompletion":true},{"repeatCount":0,"removedOnCompletion":true,"from":{"scalar":0.01},"timingFunction":"EaseOut","additive":false,"timeOffset":0,"autoreverses":false,"property":"transform.scale.xy","fillMode":"both","duration":0.75,"beginTime":0,"to":{"scalar":1}},{"additive":false,"timeOffset":0,"beginTime":0,"from":{"scalar":0},"repeatCount":0,"fillMode":"both","duration":0.75,"autoreverses":false,"property":"opacity","to":{"scalar":1},"removedOnCompletion":true},{"additive":false,"timeOffset":0,"beginTime":0,"from":{"pointX":0.5,"pointY":0.5},"repeatCount":0,"fillMode":"removed","duration":0.75,"autoreverses":false,"property":"anchorPoint","to":{"pointX":0.5,"pointY":0.5},"removedOnCompletion":true},{"additive":false,"timeOffset":0,"beginTime":0,"from":{"scalar":0},"repeatCount":0,"fillMode":"removed","duration":0.75,"autoreverses":false,"property":"transform.translation.x","to":{"scalar":0},"removedOnCompletion":true},{"additive":false,"timeOffset":0,"beginTime":0,"from":{"scalar":0},"repeatCount":0,"fillMode":"removed","duration":0.75,"autoreverses":false,"property":"transform.translation.y","to":{"scalar":0},"removedOnCompletion":true}],"removedOnCompletion":false}],"layers":[],"texturedRectangle":{"singleTextureOpacity":1,"textXHeight":0.023671232876712325,"textBaseline":0.70514331560700994,"isBackgroundTexture":true,"isVerticalText":false,"textColor":[0,0,0,1],"textureType":6},"initialState":{"affineTransform":[1,0,0,1,0,0],"masksToBounds":false,"rotation":0,"scale":1,"position":{"pointX":471.48796733220456,"pointY":102.00000365575154},"width":929,"sublayerTransform":[1,0,0,0,0,1,0,0,0,0,1,0,0,0,0,1],"contentsRect":{"y":0,"x":0,"width":1,"height":1},"opacity":1,"edgeAntialiasingMask":0,"height":146,"hidden":true,"anchorPoint":{"pointX":0.5,"pointY":0.5}},"texture":"C3D1CCE3C5DB939E97237F1C22DA967F"}]}]},"effects":[{"beginTime":0,"baseLayer":{"animations":[],"initialState":{"affineTransform":[1,0,0,1,0,0],"masksToBounds":false,"rotation":0,"scale":1,"position":{"pointX":845.65523258844996,"pointY":643.29998811086011},"width":686,"sublayerTransform":[1,0,0,0,0,1,0,0,0,0,1,0,0,0,0,1],"contentsRect":{"y":0,"x":0,"width":1,"height":1},"opacity":1,"edgeAntialiasingMask":251658240,"height":770,"hidden":false,"anchorPoint":{"pointX":0.5,"pointY":0.5}},"objectID":"4D664261-FDFB-42D2-9359-E4396B8BB9A2","layers":[{"animations":[],"initialState":{"affineTransform":[1,0,0,1,0,0],"masksToBounds":false,"rotation":0,"scale":1,"position":{"pointX":457.34476741155004,"pointY":281.70001188913989},"width":686,"sublayerTransform":[1,0,0,0,0,1,0,0,0,0,1,-0.00035007912466775983,0,0,0,1],"contentsRect":{"y":0,"x":0,"width":1,"height":1},"opacity":1,"edgeAntialiasingMask":251658240,"height":770,"hidden":false,"anchorPoint":{"pointX":0.66668333441916916,"pointY":0.36584417128459723}},"layers":[{"animations":[{"additive":false,"timeOffset":0,"beginTime":1e-100,"repeatCount":0,"fillMode":"both","duration":0.75,"autoreverses":false,"animations":[{"additive":false,"timeOffset":0,"beginTime":0,"from":{"scalar":false},"repeatCount":0,"fillMode":"forwards","duration":0.75,"autoreverses":false,"property":"hidden","to":{"scalar":false},"removedOnCompletion":true},{"repeatCount":0,"removedOnCompletion":true,"from":{"scalar":0.01},"timingFunction":"EaseOut","additive":false,"timeOffset":0,"autoreverses":false,"property":"transform.scale.xy","fillMode":"both","duration":0.75,"beginTime":0,"to":{"scalar":1}},{"additive":false,"timeOffset":0,"beginTime":0,"from":{"scalar":0},"repeatCount":0,"fillMode":"both","duration":0.75,"autoreverses":false,"property":"opacity","to":{"scalar":1},"removedOnCompletion":true},{"additive":false,"timeOffset":0,"beginTime":0,"from":{"pointX":0.5,"pointY":0.5},"repeatCount":0,"fillMode":"removed","duration":0.75,"autoreverses":false,"property":"anchorPoint","to":{"pointX":0.5,"pointY":0.5},"removedOnCompletion":true},{"additive":false,"timeOffset":0,"beginTime":0,"from":{"scalar":0},"repeatCount":0,"fillMode":"removed","duration":0.75,"autoreverses":false,"property":"transform.translation.x","to":{"scalar":0},"removedOnCompletion":true},{"additive":false,"timeOffset":0,"beginTime":0,"from":{"scalar":0},"repeatCount":0,"fillMode":"removed","duration":0.75,"autoreverses":false,"property":"transform.translation.y","to":{"scalar":0},"removedOnCompletion":true}],"removedOnCompletion":false}],"layers":[],"texturedRectangle":{"isBackgroundTexture":true,"singleTextureOpacity":1,"textureType":5,"textBaseline":0,"textXHeight":0,"isVerticalText":false},"initialState":{"affineTransform":[1,0,0,1,0,0],"masksToBounds":false,"rotation":0,"scale":1,"position":{"pointX":341.34476741154998,"pointY":383.70001188913989},"width":686,"sublayerTransform":[1,0,0,0,0,1,0,0,0,0,1,0,0,0,0,1],"contentsRect":{"y":0,"x":0,"width":1,"height":1},"opacity":1,"edgeAntialiasingMask":0,"height":770,"hidden":true,"anchorPoint":{"pointX":0.5,"pointY":0.5}},"texture":"EFF3C19DC1DDB806575AEFA5F6781351"}]}]},"effects":[{"beginTime":0,"baseLayer":{"animations":[],"initialState":{"affineTransform":[1,0,0,1,0,0],"masksToBounds":false,"rotation":0,"scale":1,"position":{"pointX":583.25861183802272,"pointY":410.73419122995927},"width":143,"sublayerTransform":[1,0,0,0,0,1,0,0,0,0,1,0,0,0,0,1],"contentsRect":{"y":0,"x":0,"width":1,"height":1},"opacity":1,"edgeAntialiasingMask":251658240,"height":71,"hidden":false,"anchorPoint":{"pointX":0.5,"pointY":0.5}},"objectID":"7E281B5B-54BF-4C0F-8AC8-02E1BB934BA6","layers":[{"animations":[],"initialState":{"affineTransform":[1,0,0,1,0,0],"masksToBounds":false,"rotation":0,"scale":1,"position":{"pointX":448.24138816197728,"pointY":164.76580877004073},"width":143,"sublayerTransform":[1,0,0,0,0,1,0,0,0,0,1,-0.00035007912466775983,0,0,0,1],"contentsRect":{"y":0,"x":0,"width":1,"height":1},"opacity":1,"edgeAntialiasingMask":251658240,"height":71,"hidden":false,"anchorPoint":{"pointX":3.134555161971869,"pointY":2.3206451939442356}},"layers":[{"animations":[{"additive":false,"timeOffset":0,"beginTime":1e-100,"repeatCount":0,"fillMode":"both","duration":0.75,"autoreverses":false,"animations":[{"additive":false,"timeOffset":0,"beginTime":0,"from":{"scalar":false},"repeatCount":0,"fillMode":"forwards","duration":0.75,"autoreverses":false,"property":"hidden","to":{"scalar":false},"removedOnCompletion":true},{"repeatCount":0,"removedOnCompletion":true,"from":{"scalar":0.01},"timingFunction":"EaseOut","additive":false,"timeOffset":0,"autoreverses":false,"property":"transform.scale.xy","fillMode":"both","duration":0.75,"beginTime":0,"to":{"scalar":1}},{"additive":false,"timeOffset":0,"beginTime":0,"from":{"scalar":0},"repeatCount":0,"fillMode":"both","duration":0.75,"autoreverses":false,"property":"opacity","to":{"scalar":1},"removedOnCompletion":true},{"additive":false,"timeOffset":0,"beginTime":0,"from":{"pointX":0.5,"pointY":0.5},"repeatCount":0,"fillMode":"removed","duration":0.75,"autoreverses":false,"property":"anchorPoint","to":{"pointX":0.5,"pointY":0.5},"removedOnCompletion":true},{"additive":false,"timeOffset":0,"beginTime":0,"from":{"scalar":0},"repeatCount":0,"fillMode":"removed","duration":0.75,"autoreverses":false,"property":"transform.translation.x","to":{"scalar":0},"removedOnCompletion":true},{"additive":false,"timeOffset":0,"beginTime":0,"from":{"scalar":0},"repeatCount":0,"fillMode":"removed","duration":0.75,"autoreverses":false,"property":"transform.translation.y","to":{"scalar":0},"removedOnCompletion":true}],"removedOnCompletion":false}],"layers":[],"texturedRectangle":{"isBackgroundTexture":true,"singleTextureOpacity":1,"textureType":5,"textBaseline":0,"textXHeight":0,"isVerticalText":false},"initialState":{"affineTransform":[1,0,0,1,0,0],"masksToBounds":false,"rotation":0,"scale":1,"position":{"pointX":69.741388161977341,"pointY":34.265808770040735},"width":143,"sublayerTransform":[1,0,0,0,0,1,0,0,0,0,1,0,0,0,0,1],"contentsRect":{"y":0,"x":0,"width":1,"height":1},"opacity":1,"edgeAntialiasingMask":0,"height":71,"hidden":true,"anchorPoint":{"pointX":0.5,"pointY":0.5}},"texture":"D21B500D2A0739DD8D73AF590CB61ADB"}]}]},"effects":[{"beginTime":0,"baseLayer":{"animations":[],"initialState":{"affineTransform":[1,0,0,1,0,0],"masksToBounds":false,"rotation":0,"scale":1,"position":{"pointX":583.25861183802272,"pointY":410.73419122995927},"width":143,"sublayerTransform":[1,0,0,0,0,1,0,0,0,0,1,0,0,0,0,1],"contentsRect":{"y":0,"x":0,"width":1,"height":1},"opacity":1,"edgeAntialiasingMask":251658240,"height":71,"hidden":false,"anchorPoint":{"pointX":0.5,"pointY":0.5}},"objectID":"7E281B5B-54BF-4C0F-8AC8-02E1BB934BA6","layers":[{"animations":[{"repeatCount":0,"removedOnCompletion":false,"from":{"pointX":70.067009463598936,"pointY":34.058753359644243},"timingFunction":"EaseInEaseOut","additive":false,"timeOffset":0,"autoreverses":false,"property":"position","fillMode":"both","duration":1,"beginTime":1e-100,"to":{"pointX":-266.33060728024719,"pointY":98.714677838810928}}],"layers":[],"texturedRectangle":{"isBackgroundTexture":true,"singleTextureOpacity":1,"textureType":5,"textBaseline":0,"textXHeight":0,"isVerticalText":false},"initialState":{"affineTransform":[1,0,0,1,0,0],"masksToBounds":false,"rotation":0,"scale":1,"position":{"pointX":70.067009463598936,"pointY":34.058753359644243},"width":143,"sublayerTransform":[1,0,0,0,0,1,0,0,0,0,1,0,0,0,0,1],"contentsRect":{"y":0,"x":0,"width":1,"height":1},"opacity":1,"edgeAntialiasingMask":0,"height":71,"hidden":false,"anchorPoint":{"pointX":0.50227707203931182,"pointY":0.49708372661413391}},"texture":"D21B500D2A0739DD8D73AF590CB61ADB"}]},"effects":[{"beginTime":0,"baseLayer":{"animations":[],"initialState":{"affineTransform":[1,0,0,1,0,0],"masksToBounds":false,"rotation":0,"scale":1,"position":{"pointX":246.86099509417659,"pointY":475.39011570912595},"width":143,"sublayerTransform":[1,0,0,0,0,1,0,0,0,0,1,0,0,0,0,1],"contentsRect":{"y":0,"x":0,"width":1,"height":1},"opacity":1,"edgeAntialiasingMask":251658240,"height":71,"hidden":false,"anchorPoint":{"pointX":0.5,"pointY":0.5}},"objectID":"7E281B5B-54BF-4C0F-8AC8-02E1BB934BA6","layers":[{"animations":[{"additive":false,"timeOffset":0,"beginTime":1e-100,"repeatCount":0,"fillMode":"both","duration":1,"autoreverses":false,"animations":[{"repeatCount":0,"removedOnCompletion":true,"from":{"scalar":1},"timingFunction":"EaseInEaseOut","additive":false,"timeOffset":0,"autoreverses":false,"property":"transform.scale.x","fillMode":"both","duration":1,"beginTime":0,"to":{"scalar":2.8672676086425781}},{"repeatCount":0,"removedOnCompletion":true,"from":{"scalar":1},"timingFunction":"EaseInEaseOut","additive":false,"timeOffset":0,"autoreverses":false,"property":"transform.scale.y","fillMode":"both","duration":1,"beginTime":0,"to":{"scalar":2.8672676086425781}}],"removedOnCompletion":false}],"layers":[],"texturedRectangle":{"isBackgroundTexture":true,"singleTextureOpacity":1,"textureType":5,"textBaseline":0,"textXHeight":0,"isVerticalText":false},"initialState":{"affineTransform":[1,0,0,1,0,0],"masksToBounds":false,"rotation":0,"scale":1,"position":{"pointX":70.067009463598936,"pointY":34.058753359644243},"width":143,"sublayerTransform":[1,0,0,0,0,1,0,0,0,0,1,0,0,0,0,1],"contentsRect":{"y":0,"x":0,"width":1,"height":1},"opacity":1,"edgeAntialiasingMask":0,"height":71,"hidden":false,"anchorPoint":{"pointX":0.50227707203931182,"pointY":0.49708372661413391}},"texture":"D21B500D2A0739DD8D73AF590CB61ADB"}]},"effects":[{"beginTime":0,"baseLayer":{"animations":[],"initialState":{"affineTransform":[1,0,0,1,0,0],"masksToBounds":false,"rotation":0,"scale":1,"position":{"pointX":767.06021206710182,"pointY":405.20638807067149},"width":386,"sublayerTransform":[1,0,0,0,0,1,0,0,0,0,1,0,0,0,0,1],"contentsRect":{"y":0,"x":0,"width":1,"height":1},"opacity":1,"edgeAntialiasingMask":251658240,"height":58,"hidden":false,"anchorPoint":{"pointX":0.5,"pointY":0.5}},"objectID":"283E3D4A-32F0-446F-A87C-33534269C248","layers":[{"animations":[],"initialState":{"affineTransform":[1,0,0,1,0,0],"masksToBounds":false,"rotation":0,"scale":1,"position":{"pointX":385.93978793289818,"pointY":163.79361192932851},"width":386,"sublayerTransform":[1,0,0,0,0,1,0,0,0,0,1,-0.00035007912466775983,0,0,0,1],"contentsRect":{"y":0,"x":0,"width":1,"height":1},"opacity":1,"edgeAntialiasingMask":251658240,"height":58,"hidden":false,"anchorPoint":{"pointX":0.99984401018885538,"pointY":2.8240277918849741}},"layers":[{"animations":[{"additive":false,"timeOffset":0,"beginTime":1e-100,"repeatCount":0,"fillMode":"both","duration":1,"autoreverses":false,"animations":[{"repeatCount":0,"removedOnCompletion":true,"from":{"scalar":0},"timingFunction":"EaseInEaseOut","additive":false,"timeOffset":0,"autoreverses":false,"property":"opacity","fillMode":"both","duration":1,"beginTime":0,"to":{"scalar":1}},{"additive":false,"timeOffset":0,"beginTime":0,"from":{"scalar":false},"repeatCount":0,"fillMode":"forwards","duration":1,"autoreverses":false,"property":"hidden","to":{"scalar":false},"removedOnCompletion":true}],"removedOnCompletion":false}],"layers":[],"texturedRectangle":{"singleTextureOpacity":1,"textXHeight":0,"shapePath":{"lineWidth":1,"flatness":0.59999999999999998,"lineCapStyle":0,"elements":[{"type":"MoveToPoint","points":[[5.5492757161443933,40.784586588542709]]},{"type":"AddLine","points":[[359.95870049464565,18.641173103773212]]}],"windingRule":0,"lineJoinStyle":0,"miterLimit":10},"isBackgroundTexture":true,"textBaseline":0,"isVerticalText":false,"textureType":5},"initialState":{"affineTransform":[1,0,0,1,0,0],"masksToBounds":false,"rotation":0,"scale":1,"position":{"pointX":191.93978793289818,"pointY":27.793611929328506},"width":386,"sublayerTransform":[1,0,0,0,0,1,0,0,0,0,1,0,0,0,0,1],"contentsRect":{"y":0,"x":0,"width":1,"height":1},"opacity":1,"edgeAntialiasingMask":0,"height":58,"hidden":true,"anchorPoint":{"pointX":0.5,"pointY":0.5}},"texture":"24BF7CAAC7FD459582A8B21E36FC6381"}]}]},"effects":[{"beginTime":0,"baseLayer":{"animations":[],"initialState":{"affineTransform":[1,0,0,1,0,0],"masksToBounds":false,"rotation":0,"scale":1,"position":{"pointX":961.37495772043894,"pointY":400.08380315701174},"width":114,"sublayerTransform":[1,0,0,0,0,1,0,0,0,0,1,0,0,0,0,1],"contentsRect":{"y":0,"x":0,"width":1,"height":1},"opacity":1,"edgeAntialiasingMask":251658240,"height":44,"hidden":false,"anchorPoint":{"pointX":0.5,"pointY":0.5}},"objectID":"26302FD9-1940-41DB-B2A5-E9CCA77838C7","layers":[{"animations":[],"initialState":{"affineTransform":[1,0,0,1,0,0],"masksToBounds":false,"rotation":0,"scale":1,"position":{"pointX":55.625042279561058,"pointY":161.91619684298826},"width":114,"sublayerTransform":[1,0,0,0,0,1,0,0,0,0,1,-0.00035007912466775983,0,0,0,1],"contentsRect":{"y":0,"x":0,"width":1,"height":1},"opacity":1,"edgeAntialiasingMask":251658240,"height":44,"hidden":false,"anchorPoint":{"pointX":0.48793896736457065,"pointY":3.6799135646133694}},"layers":[{"animations":[{"additive":false,"timeOffset":0,"beginTime":1e-100,"repeatCount":0,"fillMode":"both","duration":0.75,"autoreverses":false,"animations":[{"additive":false,"timeOffset":0,"beginTime":0,"from":{"scalar":false},"repeatCount":0,"fillMode":"forwards","duration":0.75,"autoreverses":false,"property":"hidden","to":{"scalar":false},"removedOnCompletion":true},{"repeatCount":0,"removedOnCompletion":true,"from":{"scalar":0.01},"timingFunction":"EaseOut","additive":false,"timeOffset":0,"autoreverses":false,"property":"transform.scale.xy","fillMode":"both","duration":0.75,"beginTime":0,"to":{"scalar":1}},{"additive":false,"timeOffset":0,"beginTime":0,"from":{"scalar":0},"repeatCount":0,"fillMode":"both","duration":0.75,"autoreverses":false,"property":"opacity","to":{"scalar":1},"removedOnCompletion":true},{"additive":false,"timeOffset":0,"beginTime":0,"from":{"pointX":0.5,"pointY":0.5},"repeatCount":0,"fillMode":"removed","duration":0.75,"autoreverses":false,"property":"anchorPoint","to":{"pointX":0.5,"pointY":0.5},"removedOnCompletion":true},{"additive":false,"timeOffset":0,"beginTime":0,"from":{"scalar":0},"repeatCount":0,"fillMode":"removed","duration":0.75,"autoreverses":false,"property":"transform.translation.x","to":{"scalar":0},"removedOnCompletion":true},{"additive":false,"timeOffset":0,"beginTime":0,"from":{"scalar":0},"repeatCount":0,"fillMode":"removed","duration":0.75,"autoreverses":false,"property":"transform.translation.y","to":{"scalar":0},"removedOnCompletion":true}],"removedOnCompletion":false}],"layers":[],"texturedRectangle":{"isBackgroundTexture":true,"singleTextureOpacity":1,"textureType":5,"textBaseline":0,"textXHeight":0,"isVerticalText":false},"initialState":{"affineTransform":[1,0,0,1,0,0],"masksToBounds":false,"rotation":0,"scale":1,"position":{"pointX":55.625042279561058,"pointY":20.916196842988256},"width":114,"sublayerTransform":[1,0,0,0,0,1,0,0,0,0,1,0,0,0,0,1],"contentsRect":{"y":0,"x":0,"width":1,"height":1},"opacity":1,"edgeAntialiasingMask":0,"height":44,"hidden":true,"anchorPoint":{"pointX":0.5,"pointY":0.5}},"texture":"8476563D8982227EF9FBEC92502EAADE"}]}]},"effects":[{"beginTime":0,"baseLayer":{"animations":[],"initialState":{"affineTransform":[1,0,0,1,0,0],"masksToBounds":false,"rotation":0,"scale":1,"position":{"pointX":961.37495772043894,"pointY":400.08380315701174},"width":114,"sublayerTransform":[1,0,0,0,0,1,0,0,0,0,1,0,0,0,0,1],"contentsRect":{"y":0,"x":0,"width":1,"height":1},"opacity":1,"edgeAntialiasingMask":251658240,"height":44,"hidden":false,"anchorPoint":{"pointX":0.5,"pointY":0.5}},"objectID":"26302FD9-1940-41DB-B2A5-E9CCA77838C7","layers":[{"animations":[{"repeatCount":0,"removedOnCompletion":false,"from":{"pointX":55.625041961669922,"pointY":20.488557815551758},"timingFunction":"EaseInEaseOut","additive":false,"timeOffset":0,"autoreverses":false,"property":"position","fillMode":"both","duration":1,"beginTime":1e-100,"to":{"pointX":644.33109919230174,"pointY":20.488557815551928}}],"layers":[],"texturedRectangle":{"isBackgroundTexture":true,"singleTextureOpacity":1,"textureType":5,"textBaseline":0,"textXHeight":0,"isVerticalText":false},"initialState":{"affineTransform":[1,0,0,1,0,0],"masksToBounds":false,"rotation":0,"scale":1,"position":{"pointX":55.625041961669922,"pointY":20.488557815551758},"width":114,"sublayerTransform":[1,0,0,0,0,1,0,0,0,0,1,0,0,0,0,1],"contentsRect":{"y":0,"x":0,"width":1,"height":1},"opacity":1,"edgeAntialiasingMask":0,"height":44,"hidden":false,"anchorPoint":{"pointX":0.49999999721148125,"pointY":0.49028093119462501}},"texture":"8476563D8982227EF9FBEC92502EAADE"}]},"effects":[{"beginTime":0,"baseLayer":{"animations":[],"initialState":{"affineTransform":[1,0,0,1,0,0],"masksToBounds":false,"rotation":0,"scale":1,"position":{"pointX":1550.0810149510708,"pointY":400.08380315701191},"width":114,"sublayerTransform":[1,0,0,0,0,1,0,0,0,0,1,0,0,0,0,1],"contentsRect":{"y":0,"x":0,"width":1,"height":1},"opacity":1,"edgeAntialiasingMask":251658240,"height":44,"hidden":false,"anchorPoint":{"pointX":0.5,"pointY":0.5}},"objectID":"26302FD9-1940-41DB-B2A5-E9CCA77838C7","layers":[{"animations":[{"additive":false,"timeOffset":0,"beginTime":1e-100,"repeatCount":0,"fillMode":"both","duration":1,"autoreverses":false,"animations":[{"repeatCount":0,"removedOnCompletion":true,"from":{"scalar":1},"timingFunction":"EaseInEaseOut","additive":false,"timeOffset":0,"autoreverses":false,"property":"transform.scale.x","fillMode":"both","duration":1,"beginTime":0,"to":{"scalar":5.9152092933654785}},{"repeatCount":0,"removedOnCompletion":true,"from":{"scalar":1},"timingFunction":"EaseInEaseOut","additive":false,"timeOffset":0,"autoreverses":false,"property":"transform.scale.y","fillMode":"both","duration":1,"beginTime":0,"to":{"scalar":5.9152092933654785}}],"removedOnCompletion":false}],"layers":[],"texturedRectangle":{"isBackgroundTexture":true,"singleTextureOpacity":1,"textureType":5,"textBaseline":0,"textXHeight":0,"isVerticalText":false},"initialState":{"affineTransform":[1,0,0,1,0,0],"masksToBounds":false,"rotation":0,"scale":1,"position":{"pointX":55.625041961669922,"pointY":20.488557815551758},"width":114,"sublayerTransform":[1,0,0,0,0,1,0,0,0,0,1,0,0,0,0,1],"contentsRect":{"y":0,"x":0,"width":1,"height":1},"opacity":1,"edgeAntialiasingMask":0,"height":44,"hidden":false,"anchorPoint":{"pointX":0.49999999721148125,"pointY":0.49028093119462501}},"texture":"8476563D8982227EF9FBEC92502EAADE"}]},"effects":[{"beginTime":0,"baseLayer":{"animations":[],"initialState":{"affineTransform":[1,0,0,1,0,0],"masksToBounds":false,"rotation":0,"scale":1,"position":{"pointX":1451.3706930701737,"pointY":837.00502427419008},"width":482,"sublayerTransform":[1,0,0,0,0,1,0,0,0,0,1,0,0,0,0,1],"contentsRect":{"y":0,"x":0,"width":1,"height":1},"opacity":1,"edgeAntialiasingMask":251658240,"height":425,"hidden":false,"anchorPoint":{"pointX":0.5,"pointY":0.5}},"objectID":"1476BD1E-EAAC-4B8A-ACB6-1C54DE790211","layers":[{"animations":[],"initialState":{"affineTransform":[1,0,0,1,0,0],"masksToBounds":false,"rotation":0,"scale":1,"position":{"pointX":-250.37069307017373,"pointY":-84.505024274190077},"width":482,"sublayerTransform":[1,0,0,0,0,1,0,0,0,0,1,-0.00035007912466775983,0,0,0,1],"contentsRect":{"y":0,"x":0,"width":1,"height":1},"opacity":1,"edgeAntialiasingMask":251658240,"height":425,"hidden":false,"anchorPoint":{"pointX":-0.51944127192982104,"pointY":-0.19883535123338841}},"layers":[{"animations":[{"additive":false,"timeOffset":0,"beginTime":1e-100,"repeatCount":0,"fillMode":"both","duration":0.75,"autoreverses":false,"animations":[{"additive":false,"timeOffset":0,"beginTime":0,"from":{"scalar":false},"repeatCount":0,"fillMode":"forwards","duration":0.75,"autoreverses":false,"property":"hidden","to":{"scalar":false},"removedOnCompletion":true},{"repeatCount":0,"removedOnCompletion":true,"from":{"scalar":0.01},"timingFunction":"EaseOut","additive":false,"timeOffset":0,"autoreverses":false,"property":"transform.scale.xy","fillMode":"both","duration":0.75,"beginTime":0,"to":{"scalar":1}},{"additive":false,"timeOffset":0,"beginTime":0,"from":{"scalar":0},"repeatCount":0,"fillMode":"both","duration":0.75,"autoreverses":false,"property":"opacity","to":{"scalar":1},"removedOnCompletion":true},{"additive":false,"timeOffset":0,"beginTime":0,"from":{"pointX":0.5,"pointY":0.5},"repeatCount":0,"fillMode":"removed","duration":0.75,"autoreverses":false,"property":"anchorPoint","to":{"pointX":0.5,"pointY":0.5},"removedOnCompletion":true},{"additive":false,"timeOffset":0,"beginTime":0,"from":{"scalar":0},"repeatCount":0,"fillMode":"removed","duration":0.75,"autoreverses":false,"property":"transform.translation.x","to":{"scalar":0},"removedOnCompletion":true},{"additive":false,"timeOffset":0,"beginTime":0,"from":{"scalar":0},"repeatCount":0,"fillMode":"removed","duration":0.75,"autoreverses":false,"property":"transform.translation.y","to":{"scalar":0},"removedOnCompletion":true}],"removedOnCompletion":false}],"layers":[],"texturedRectangle":{"isBackgroundTexture":true,"singleTextureOpacity":1,"textureType":5,"textBaseline":0,"textXHeight":0,"isVerticalText":false},"initialState":{"affineTransform":[1,0,0,1,0,0],"masksToBounds":false,"rotation":0,"scale":1,"position":{"pointX":239.62930692982627,"pointY":210.99497572580992},"width":482,"sublayerTransform":[1,0,0,0,0,1,0,0,0,0,1,0,0,0,0,1],"contentsRect":{"y":0,"x":0,"width":1,"height":1},"opacity":1,"edgeAntialiasingMask":0,"height":425,"hidden":true,"anchorPoint":{"pointX":0.5,"pointY":0.5}},"texture":"B28C276801367825A84224717157A0E8"}]}]},"effects":[{"beginTime":0,"baseLayer":{"animations":[],"initialState":{"affineTransform":[1,0,0,1,0,0],"masksToBounds":false,"rotation":0,"scale":1,"position":{"pointX":1418.5749855142908,"pointY":645.4731250204552},"width":76,"sublayerTransform":[1,0,0,0,0,1,0,0,0,0,1,0,0,0,0,1],"contentsRect":{"y":0,"x":0,"width":1,"height":1},"opacity":1,"edgeAntialiasingMask":251658240,"height":341,"hidden":false,"anchorPoint":{"pointX":0.5,"pointY":0.5}},"objectID":"F287EAC6-4593-425B-B1CE-8734C4ADF207","layers":[{"animations":[],"initialState":{"affineTransform":[1,0,0,1,0,0],"masksToBounds":false,"rotation":0,"scale":1,"position":{"pointX":-420.5749855142908,"pointY":65.0268749795448},"width":76,"sublayerTransform":[1,0,0,0,0,1,0,0,0,0,1,-0.00035007912466775983,0,0,0,1],"contentsRect":{"y":0,"x":0,"width":1,"height":1},"opacity":1,"edgeAntialiasingMask":251658240,"height":341,"hidden":false,"anchorPoint":{"pointX":-5.5338813883459315,"pointY":0.19069464803385572}},"layers":[{"animations":[{"additive":false,"timeOffset":0,"beginTime":1e-100,"repeatCount":0,"fillMode":"both","duration":1,"autoreverses":false,"animations":[{"repeatCount":0,"removedOnCompletion":true,"from":{"scalar":0},"timingFunction":"EaseInEaseOut","additive":false,"timeOffset":0,"autoreverses":false,"property":"opacity","fillMode":"both","duration":1,"beginTime":0,"to":{"scalar":1}},{"additive":false,"timeOffset":0,"beginTime":0,"from":{"scalar":false},"repeatCount":0,"fillMode":"forwards","duration":1,"autoreverses":false,"property":"hidden","to":{"scalar":false},"removedOnCompletion":true}],"removedOnCompletion":false}],"layers":[],"texturedRectangle":{"singleTextureOpacity":1,"textXHeight":0,"shapePath":{"lineWidth":1,"flatness":0.59999999999999998,"lineCapStyle":0,"elements":[{"type":"MoveToPoint","points":[[58.408708026488739,7.4130583289691003]]},{"type":"AddLine","points":[[20.340053170897818,313.30146952349423]]}],"windingRule":0,"lineJoinStyle":0,"miterLimit":10},"isBackgroundTexture":true,"textBaseline":0,"isVerticalText":false,"textureType":5},"initialState":{"affineTransform":[1,0,0,1,0,0],"masksToBounds":false,"rotation":0,"scale":1,"position":{"pointX":36.425014485709198,"pointY":168.52687497954474},"width":76,"sublayerTransform":[1,0,0,0,0,1,0,0,0,0,1,0,0,0,0,1],"contentsRect":{"y":0,"x":0,"width":1,"height":1},"opacity":1,"edgeAntialiasingMask":0,"height":341,"hidden":true,"anchorPoint":{"pointX":0.5,"pointY":0.5}},"texture":"1C2D85C57D1BBC48B0C74B45B529F370"}]}]},"effects":[{"beginTime":0,"baseLayer":{"animations":[],"initialState":{"affineTransform":[1,0,0,1,0,0],"masksToBounds":false,"rotation":0,"scale":1,"position":{"pointX":1814.8333333333335,"pointY":994.8333333333336},"width":103,"sublayerTransform":[1,0,0,0,0,1,0,0,0,0,1,0,0,0,0,1],"contentsRect":{"y":0,"x":0,"width":1,"height":1},"opacity":1,"edgeAntialiasingMask":251658240,"height":103,"hidden":false,"anchorPoint":{"pointX":0.5,"pointY":0.5}},"objectID":"6C72FF63-09FE-46FA-AECF-32DF39E1696C","layers":[{"animations":[],"initialState":{"affineTransform":[1,0,0,1,0,0],"masksToBounds":false,"rotation":0,"scale":1,"position":{"pointX":-803.33333333333348,"pointY":-403.3333333333336},"width":103,"sublayerTransform":[1,0,0,0,0,1,0,0,0,0,1,-0.00035007912466775983,0,0,0,1],"contentsRect":{"y":0,"x":0,"width":1,"height":1},"opacity":1,"edgeAntialiasingMask":251658240,"height":103,"hidden":false,"anchorPoint":{"pointX":-7.7993527508090628,"pointY":-3.9158576051779961}},"layers":[{"animations":[{"additive":false,"timeOffset":0,"beginTime":1e-100,"repeatCount":0,"fillMode":"both","duration":0.75,"autoreverses":false,"animations":[{"additive":false,"timeOffset":0,"beginTime":0,"from":{"scalar":false},"repeatCount":0,"fillMode":"forwards","duration":0.75,"autoreverses":false,"property":"hidden","to":{"scalar":false},"removedOnCompletion":true},{"repeatCount":0,"removedOnCompletion":true,"from":{"scalar":0.01},"timingFunction":"EaseOut","additive":false,"timeOffset":0,"autoreverses":false,"property":"transform.scale.xy","fillMode":"both","duration":0.75,"beginTime":0,"to":{"scalar":1}},{"additive":false,"timeOffset":0,"beginTime":0,"from":{"scalar":0},"repeatCount":0,"fillMode":"both","duration":0.75,"autoreverses":false,"property":"opacity","to":{"scalar":1},"removedOnCompletion":true},{"additive":false,"timeOffset":0,"beginTime":0,"from":{"pointX":0.5,"pointY":0.5},"repeatCount":0,"fillMode":"removed","duration":0.75,"autoreverses":false,"property":"anchorPoint","to":{"pointX":0.5,"pointY":0.5},"removedOnCompletion":true},{"additive":false,"timeOffset":0,"beginTime":0,"from":{"scalar":0},"repeatCount":0,"fillMode":"removed","duration":0.75,"autoreverses":false,"property":"transform.translation.x","to":{"scalar":0},"removedOnCompletion":true},{"additive":false,"timeOffset":0,"beginTime":0,"from":{"scalar":0},"repeatCount":0,"fillMode":"removed","duration":0.75,"autoreverses":false,"property":"transform.translation.y","to":{"scalar":0},"removedOnCompletion":true}],"removedOnCompletion":false}],"layers":[],"texturedRectangle":{"singleTextureOpacity":1,"textXHeight":0,"shapePath":{"lineWidth":1,"flatness":0.59999999999999998,"lineCapStyle":0,"elements":[{"type":"MoveToPoint","points":[[37.333333333333485,67.333333333333599]]},{"type":"AddLine","points":[[37.333333333333485,101.33333333333348]]},{"type":"AddLine","points":[[101.33333333333348,51.333333333333599]]},{"type":"AddLine","points":[[37.333333333333485,1.3333333333335986]]},{"type":"AddLine","points":[[37.333333333333485,35.333333333333599]]},{"type":"AddLine","points":[[1.3333333333334849,35.333333333333599]]},{"type":"AddLine","points":[[1.3333333333334849,67.333333333333599]]},{"type":"CloseSubpath"}],"windingRule":0,"lineJoinStyle":0,"miterLimit":10},"isBackgroundTexture":true,"textBaseline":0,"isVerticalText":false,"textureType":5},"initialState":{"affineTransform":[1,0,0,1,0,0],"masksToBounds":false,"rotation":0,"scale":1,"position":{"pointX":50.166666666666515,"pointY":50.166666666666401},"width":103,"sublayerTransform":[1,0,0,0,0,1,0,0,0,0,1,0,0,0,0,1],"contentsRect":{"y":0,"x":0,"width":1,"height":1},"opacity":1,"edgeAntialiasingMask":0,"height":103,"hidden":true,"anchorPoint":{"pointX":0.5,"pointY":0.5}},"texture":"5FF86E2A824437EFAD54AE3258E09603"}]}]},"effects":[{"beginTime":0,"baseLayer":{"animations":[],"initialState":{"affineTransform":[1,0,0,1,0,0],"masksToBounds":false,"rotation":0,"scale":1,"position":{"pointX":225.41771697998041,"pointY":971.99241129557299},"width":209,"sublayerTransform":[1,0,0,0,0,1,0,0,0,0,1,0,0,0,0,1],"contentsRect":{"y":0,"x":0,"width":1,"height":1},"opacity":1,"edgeAntialiasingMask":251658240,"height":90,"hidden":false,"anchorPoint":{"pointX":0.5,"pointY":0.5}},"objectID":"2DDF3F28-3408-4863-AE96-722F78A6951A","layers":[{"animations":[],"initialState":{"affineTransform":[1,0,0,1,0,0],"masksToBounds":false,"rotation":0,"scale":1,"position":{"pointX":839.08228302001953,"pointY":-386.99241129557299},"width":209,"sublayerTransform":[1,0,0,0,0,1,0,0,0,0,1,-0.00035007912466775983,0,0,0,1],"contentsRect":{"y":0,"x":0,"width":1,"height":1},"opacity":1,"edgeAntialiasingMask":251658240,"height":90,"hidden":false,"anchorPoint":{"pointX":4.0147477656460264,"pointY":-4.2999156810619219}},"layers":[{"animations":[{"additive":false,"timeOffset":0,"beginTime":1e-100,"repeatCount":0,"fillMode":"both","duration":0.75,"autoreverses":false,"animations":[{"additive":false,"timeOffset":0,"beginTime":0,"from":{"scalar":false},"repeatCount":0,"fillMode":"forwards","duration":0.75,"autoreverses":false,"property":"hidden","to":{"scalar":false},"removedOnCompletion":true},{"repeatCount":0,"removedOnCompletion":true,"from":{"scalar":0.01},"timingFunction":"EaseOut","additive":false,"timeOffset":0,"autoreverses":false,"property":"transform.scale.xy","fillMode":"both","duration":0.75,"beginTime":0,"to":{"scalar":1}},{"additive":false,"timeOffset":0,"beginTime":0,"from":{"scalar":0},"repeatCount":0,"fillMode":"both","duration":0.75,"autoreverses":false,"property":"opacity","to":{"scalar":1},"removedOnCompletion":true},{"additive":false,"timeOffset":0,"beginTime":0,"from":{"pointX":0.5,"pointY":0.5},"repeatCount":0,"fillMode":"removed","duration":0.75,"autoreverses":false,"property":"anchorPoint","to":{"pointX":0.5,"pointY":0.5},"removedOnCompletion":true},{"additive":false,"timeOffset":0,"beginTime":0,"from":{"scalar":0},"repeatCount":0,"fillMode":"removed","duration":0.75,"autoreverses":false,"property":"transform.translation.x","to":{"scalar":0},"removedOnCompletion":true},{"additive":false,"timeOffset":0,"beginTime":0,"from":{"scalar":0},"repeatCount":0,"fillMode":"removed","duration":0.75,"autoreverses":false,"property":"transform.translation.y","to":{"scalar":0},"removedOnCompletion":true}],"removedOnCompletion":false}],"layers":[],"texturedRectangle":{"isBackgroundTexture":true,"singleTextureOpacity":1,"textureType":5,"textBaseline":0,"textXHeight":0,"isVerticalText":false},"initialState":{"affineTransform":[1,0,0,1,0,0],"masksToBounds":false,"rotation":0,"scale":1,"position":{"pointX":102.58228302001957,"pointY":43.007588704427008},"width":209,"sublayerTransform":[1,0,0,0,0,1,0,0,0,0,1,0,0,0,0,1],"contentsRect":{"y":0,"x":0,"width":1,"height":1},"opacity":1,"edgeAntialiasingMask":0,"height":90,"hidden":true,"anchorPoint":{"pointX":0.5,"pointY":0.5}},"texture":"B2F0BCA7C2A8885167BA19674E52A20A"}]}]},"effects":[],"duration":0.75,"type":"buildIn","attributes":{"direction":43},"name":"apple:zoom","objectID":"2DDF3F28-3408-4863-AE96-722F78A6951A"}],"duration":0.75,"type":"buildIn","attributes":{"direction":43},"name":"apple:zoom character","objectID":"6C72FF63-09FE-46FA-AECF-32DF39E1696C"}],"duration":1,"type":"buildIn","attributes":{"direction":11},"name":"apple:wipe","objectID":"F287EAC6-4593-425B-B1CE-8734C4ADF207"}],"duration":0.75,"type":"buildIn","attributes":{"direction":43},"name":"apple:zoom","objectID":"1476BD1E-EAAC-4B8A-ACB6-1C54DE790211"}],"duration":1,"type":"actionBuild","attributes":{"direction":0},"name":"apple:action-scale","objectID":"26302FD9-1940-41DB-B2A5-E9CCA77838C7"}],"duration":1,"type":"actionBuild","attributes":{"direction":0},"name":"apple:action-motion-path","objectID":"26302FD9-1940-41DB-B2A5-E9CCA77838C7"}],"duration":0.75,"type":"buildIn","attributes":{"direction":43},"name":"apple:zoom","objectID":"26302FD9-1940-41DB-B2A5-E9CCA77838C7"}],"duration":1,"type":"buildIn","attributes":{"direction":11},"name":"apple:wipe","objectID":"283E3D4A-32F0-446F-A87C-33534269C248"}],"duration":1,"type":"actionBuild","attributes":{"direction":0},"name":"apple:action-scale","objectID":"7E281B5B-54BF-4C0F-8AC8-02E1BB934BA6"}],"duration":1,"type":"actionBuild","attributes":{"direction":0},"name":"apple:action-motion-path","objectID":"7E281B5B-54BF-4C0F-8AC8-02E1BB934BA6"}],"duration":0.75,"type":"buildIn","attributes":{"direction":43},"name":"apple:zoom","objectID":"7E281B5B-54BF-4C0F-8AC8-02E1BB934BA6"}],"duration":0.75,"type":"buildIn","attributes":{"direction":43},"name":"apple:zoom","objectID":"4D664261-FDFB-42D2-9359-E4396B8BB9A2"}],"duration":0.75,"type":"buildIn","attributes":{"direction":43},"name":"apple:zoom character","objectID":"AB6BDAF9-BBF8-4D6D-9832-43AEF85F30BD"}],"automaticPlay":true,"hyperlinks":[],"accessibility":[{"text":"vídeo-pegado.png","targetRectangle":{"y":-5.671875,"x":-4.4353184700012207,"width":2165.380126953125,"height":1091.34375}},{"text":"Volver","targetRectangle":{"y":942.33365766207385,"x":158.09701538085932,"width":130.65600000000001,"height":55.656005859375}}],"baseLayer":{"animations":[],"initialState":{"affineTransform":[1,0,0,1,0,0],"masksToBounds":false,"rotation":0,"scale":1,"position":{"pointX":960,"pointY":540},"width":1920,"sublayerTransform":[1,0,0,0,0,1,0,0,0,0,1,0,0,0,0,1],"contentsRect":{"y":0,"x":0,"width":1,"height":1},"opacity":1,"edgeAntialiasingMask":251658240,"height":1080,"hidden":false,"anchorPoint":{"pointX":0.5,"pointY":0.5}},"layers":[{"animations":[],"initialState":{"affineTransform":[1,0,0,1,0,0],"masksToBounds":false,"rotation":0,"scale":1,"position":{"pointX":960,"pointY":540},"width":1920,"sublayerTransform":[1,0,0,0,0,1,0,0,0,0,1,0,0,0,0,1],"contentsRect":{"y":0,"x":0,"width":1,"height":1},"opacity":1,"edgeAntialiasingMask":251658240,"height":1080,"hidden":false,"anchorPoint":{"pointX":0.5,"pointY":0.5}},"layers":[{"animations":[],"initialState":{"affineTransform":[1,0,0,1,0,0],"masksToBounds":false,"rotation":0,"scale":1,"position":{"pointX":960,"pointY":540},"width":1920,"sublayerTransform":[1,0,0,0,0,1,0,0,0,0,1,0,0,0,0,1],"contentsRect":{"y":0,"x":0,"width":1,"height":1},"opacity":1,"edgeAntialiasingMask":251658240,"height":1080,"hidden":false,"anchorPoint":{"pointX":0.5,"pointY":0.5}},"layers":[{"animations":[],"layers":[],"texturedRectangle":{"isBackgroundTexture":true,"singleTextureOpacity":1,"textureType":1,"textBaseline":0,"textXHeight":0,"isVerticalText":false},"initialState":{"affineTransform":[1,0,0,1,0,0],"masksToBounds":false,"rotation":0,"scale":1,"position":{"pointX":960,"pointY":540},"width":1920,"sublayerTransform":[1,0,0,0,0,1,0,0,0,0,1,0,0,0,0,1],"contentsRect":{"y":0,"x":0,"width":1,"height":1},"opacity":1,"edgeAntialiasingMask":0,"height":1080,"hidden":false,"anchorPoint":{"pointX":0.5,"pointY":0.5}},"texture":"C25C25FF361FB24FC35F6B120D2F252D"}]}]},{"animations":[],"initialState":{"affineTransform":[1,0,0,1,0,0],"masksToBounds":false,"rotation":0,"scale":1,"position":{"pointX":960,"pointY":540},"width":1920,"sublayerTransform":[1,0,0,0,0,1,0,0,0,0,1,0,0,0,0,1],"contentsRect":{"y":0,"x":0,"width":1,"height":1},"opacity":1,"edgeAntialiasingMask":251658240,"height":1080,"hidden":false,"anchorPoint":{"pointX":0.5,"pointY":0.5}},"layers":[{"animations":[],"initialState":{"affineTransform":[1,0,0,1,0,0],"masksToBounds":false,"rotation":0,"scale":1,"position":{"pointX":1079.5646815299988,"pointY":541.328125},"width":2168,"sublayerTransform":[1,0,0,0,0,1,0,0,0,0,1,0,0,0,0,1],"contentsRect":{"y":0,"x":0,"width":1,"height":1},"opacity":1,"edgeAntialiasingMask":251658240,"height":1094,"hidden":false,"anchorPoint":{"pointX":0.5,"pointY":0.5}},"layers":[{"animations":[],"layers":[],"texturedRectangle":{"isBackgroundTexture":true,"singleTextureOpacity":1,"textureType":5,"textBaseline":0,"textXHeight":0,"isVerticalText":false},"initialState":{"affineTransform":[1,0,0,1,0,0],"masksToBounds":false,"rotation":0,"scale":1,"position":{"pointX":1082.4353184700012,"pointY":545.671875},"width":2168,"sublayerTransform":[1,0,0,0,0,1,0,0,0,0,1,0,0,0,0,1],"contentsRect":{"y":0,"x":0,"width":1,"height":1},"opacity":1,"edgeAntialiasingMask":0,"height":1094,"hidden":false,"anchorPoint":{"pointX":0.5,"pointY":0.5}},"texture":"C12B6BF5A5E74E88C4963D707DCDDFDD"}]}]},{"animations":[],"initialState":{"affineTransform":[1,0,0,1,0,0],"masksToBounds":false,"rotation":0,"scale":1,"position":{"pointX":960,"pointY":540},"width":1920,"sublayerTransform":[1,0,0,0,0,1,0,0,0,0,1,0,0,0,0,1],"contentsRect":{"y":0,"x":0,"width":1,"height":1},"opacity":1,"edgeAntialiasingMask":251658240,"height":1080,"hidden":false,"anchorPoint":{"pointX":0.5,"pointY":0.5}},"layers":[{"animations":[],"initialState":{"affineTransform":[1,0,0,1,0,0],"masksToBounds":false,"rotation":0,"scale":1,"position":{"pointX":583.25861183802272,"pointY":410.73419122995927},"width":143,"sublayerTransform":[1,0,0,0,0,1,0,0,0,0,1,0,0,0,0,1],"contentsRect":{"y":0,"x":0,"width":1,"height":1},"opacity":1,"edgeAntialiasingMask":251658240,"height":71,"hidden":false,"anchorPoint":{"pointX":0.5,"pointY":0.5}},"objectID":"7E281B5B-54BF-4C0F-8AC8-02E1BB934BA6","layers":[{"animations":[],"layers":[],"texturedRectangle":{"isBackgroundTexture":true,"singleTextureOpacity":1,"textureType":5,"textBaseline":0,"textXHeight":0,"isVerticalText":false},"initialState":{"affineTransform":[1,0,0,1,0,0],"masksToBounds":false,"rotation":0,"scale":1,"position":{"pointX":69.741388161977341,"pointY":34.265808770040735},"width":143,"sublayerTransform":[1,0,0,0,0,1,0,0,0,0,1,0,0,0,0,1],"contentsRect":{"y":0,"x":0,"width":1,"height":1},"opacity":1,"edgeAntialiasingMask":0,"height":71,"hidden":true,"anchorPoint":{"pointX":0.5,"pointY":0.5}},"texture":"D21B500D2A0739DD8D73AF590CB61ADB"}]}]},{"animations":[],"initialState":{"affineTransform":[1,0,0,1,0,0],"masksToBounds":false,"rotation":0,"scale":1,"position":{"pointX":960,"pointY":540},"width":1920,"sublayerTransform":[1,0,0,0,0,1,0,0,0,0,1,0,0,0,0,1],"contentsRect":{"y":0,"x":0,"width":1,"height":1},"opacity":1,"edgeAntialiasingMask":251658240,"height":1080,"hidden":false,"anchorPoint":{"pointX":0.5,"pointY":0.5}},"layers":[{"animations":[],"initialState":{"affineTransform":[1,0,0,1,0,0],"masksToBounds":false,"rotation":0,"scale":1,"position":{"pointX":845.65523258844996,"pointY":643.29998811086011},"width":686,"sublayerTransform":[1,0,0,0,0,1,0,0,0,0,1,0,0,0,0,1],"contentsRect":{"y":0,"x":0,"width":1,"height":1},"opacity":1,"edgeAntialiasingMask":251658240,"height":770,"hidden":false,"anchorPoint":{"pointX":0.5,"pointY":0.5}},"objectID":"4D664261-FDFB-42D2-9359-E4396B8BB9A2","layers":[{"animations":[],"layers":[],"texturedRectangle":{"isBackgroundTexture":true,"singleTextureOpacity":1,"textureType":5,"textBaseline":0,"textXHeight":0,"isVerticalText":false},"initialState":{"affineTransform":[1,0,0,1,0,0],"masksToBounds":false,"rotation":0,"scale":1,"position":{"pointX":341.34476741154998,"pointY":383.70001188913989},"width":686,"sublayerTransform":[1,0,0,0,0,1,0,0,0,0,1,0,0,0,0,1],"contentsRect":{"y":0,"x":0,"width":1,"height":1},"opacity":1,"edgeAntialiasingMask":0,"height":770,"hidden":true,"anchorPoint":{"pointX":0.5,"pointY":0.5}},"texture":"EFF3C19DC1DDB806575AEFA5F6781351"}]}]},{"animations":[],"initialState":{"affineTransform":[1,0,0,1,0,0],"masksToBounds":false,"rotation":0,"scale":1,"position":{"pointX":960,"pointY":540},"width":1920,"sublayerTransform":[1,0,0,0,0,1,0,0,0,0,1,0,0,0,0,1],"contentsRect":{"y":0,"x":0,"width":1,"height":1},"opacity":1,"edgeAntialiasingMask":251658240,"height":1080,"hidden":false,"anchorPoint":{"pointX":0.5,"pointY":0.5}},"layers":[{"animations":[],"initialState":{"affineTransform":[1,0,0,1,0,0],"masksToBounds":false,"rotation":0,"scale":1,"position":{"pointX":961.37495772043894,"pointY":400.08380315701174},"width":114,"sublayerTransform":[1,0,0,0,0,1,0,0,0,0,1,0,0,0,0,1],"contentsRect":{"y":0,"x":0,"width":1,"height":1},"opacity":1,"edgeAntialiasingMask":251658240,"height":44,"hidden":false,"anchorPoint":{"pointX":0.5,"pointY":0.5}},"objectID":"26302FD9-1940-41DB-B2A5-E9CCA77838C7","layers":[{"animations":[],"layers":[],"texturedRectangle":{"isBackgroundTexture":true,"singleTextureOpacity":1,"textureType":5,"textBaseline":0,"textXHeight":0,"isVerticalText":false},"initialState":{"affineTransform":[1,0,0,1,0,0],"masksToBounds":false,"rotation":0,"scale":1,"position":{"pointX":55.625042279561058,"pointY":20.916196842988256},"width":114,"sublayerTransform":[1,0,0,0,0,1,0,0,0,0,1,0,0,0,0,1],"contentsRect":{"y":0,"x":0,"width":1,"height":1},"opacity":1,"edgeAntialiasingMask":0,"height":44,"hidden":true,"anchorPoint":{"pointX":0.5,"pointY":0.5}},"texture":"8476563D8982227EF9FBEC92502EAADE"}]}]},{"animations":[],"initialState":{"affineTransform":[1,0,0,1,0,0],"masksToBounds":false,"rotation":0,"scale":1,"position":{"pointX":960,"pointY":540},"width":1920,"sublayerTransform":[1,0,0,0,0,1,0,0,0,0,1,0,0,0,0,1],"contentsRect":{"y":0,"x":0,"width":1,"height":1},"opacity":1,"edgeAntialiasingMask":251658240,"height":1080,"hidden":false,"anchorPoint":{"pointX":0.5,"pointY":0.5}},"layers":[{"animations":[],"initialState":{"affineTransform":[1,0,0,1,0,0],"masksToBounds":false,"rotation":0,"scale":1,"position":{"pointX":837.51203266779544,"pointY":79.999996344248459},"width":929,"sublayerTransform":[1,0,0,0,0,1,0,0,0,0,1,0,0,0,0,1],"contentsRect":{"y":0,"x":0,"width":1,"height":1},"opacity":1,"edgeAntialiasingMask":251658240,"height":146,"hidden":false,"anchorPoint":{"pointX":0.5,"pointY":0.5}},"objectID":"AB6BDAF9-BBF8-4D6D-9832-43AEF85F30BD","layers":[{"animations":[],"layers":[],"texturedRectangle":{"singleTextureOpacity":1,"textXHeight":0.023671232876712325,"textBaseline":0.70514331560700994,"isBackgroundTexture":true,"isVerticalText":false,"textColor":[0,0,0,1],"textureType":6},"initialState":{"affineTransform":[1,0,0,1,0,0],"masksToBounds":false,"rotation":0,"scale":1,"position":{"pointX":471.48796733220456,"pointY":102.00000365575154},"width":929,"sublayerTransform":[1,0,0,0,0,1,0,0,0,0,1,0,0,0,0,1],"contentsRect":{"y":0,"x":0,"width":1,"height":1},"opacity":1,"edgeAntialiasingMask":0,"height":146,"hidden":true,"anchorPoint":{"pointX":0.5,"pointY":0.5}},"texture":"C3D1CCE3C5DB939E97237F1C22DA967F"}]}]},{"animations":[],"initialState":{"affineTransform":[1,0,0,1,0,0],"masksToBounds":false,"rotation":0,"scale":1,"position":{"pointX":960,"pointY":540},"width":1920,"sublayerTransform":[1,0,0,0,0,1,0,0,0,0,1,0,0,0,0,1],"contentsRect":{"y":0,"x":0,"width":1,"height":1},"opacity":1,"edgeAntialiasingMask":251658240,"height":1080,"hidden":false,"anchorPoint":{"pointX":0.5,"pointY":0.5}},"layers":[{"animations":[],"initialState":{"affineTransform":[1,0,0,1,0,0],"masksToBounds":false,"rotation":0,"scale":1,"position":{"pointX":767.06021206710182,"pointY":405.20638807067149},"width":386,"sublayerTransform":[1,0,0,0,0,1,0,0,0,0,1,0,0,0,0,1],"contentsRect":{"y":0,"x":0,"width":1,"height":1},"opacity":1,"edgeAntialiasingMask":251658240,"height":58,"hidden":false,"anchorPoint":{"pointX":0.5,"pointY":0.5}},"objectID":"283E3D4A-32F0-446F-A87C-33534269C248","layers":[{"animations":[],"layers":[],"texturedRectangle":{"singleTextureOpacity":1,"textXHeight":0,"shapePath":{"lineWidth":1,"flatness":0.59999999999999998,"lineCapStyle":0,"elements":[{"type":"MoveToPoint","points":[[5.5492757161443933,40.784586588542709]]},{"type":"AddLine","points":[[359.95870049464565,18.641173103773212]]}],"windingRule":0,"lineJoinStyle":0,"miterLimit":10},"isBackgroundTexture":true,"textBaseline":0,"isVerticalText":false,"textureType":5},"initialState":{"affineTransform":[1,0,0,1,0,0],"masksToBounds":false,"rotation":0,"scale":1,"position":{"pointX":191.93978793289818,"pointY":27.793611929328506},"width":386,"sublayerTransform":[1,0,0,0,0,1,0,0,0,0,1,0,0,0,0,1],"contentsRect":{"y":0,"x":0,"width":1,"height":1},"opacity":1,"edgeAntialiasingMask":0,"height":58,"hidden":true,"anchorPoint":{"pointX":0.5,"pointY":0.5}},"texture":"24BF7CAAC7FD459582A8B21E36FC6381"}]}]},{"animations":[],"initialState":{"affineTransform":[1,0,0,1,0,0],"masksToBounds":false,"rotation":0,"scale":1,"position":{"pointX":960,"pointY":540},"width":1920,"sublayerTransform":[1,0,0,0,0,1,0,0,0,0,1,0,0,0,0,1],"contentsRect":{"y":0,"x":0,"width":1,"height":1},"opacity":1,"edgeAntialiasingMask":251658240,"height":1080,"hidden":false,"anchorPoint":{"pointX":0.5,"pointY":0.5}},"layers":[{"animations":[],"initialState":{"affineTransform":[1,0,0,1,0,0],"masksToBounds":false,"rotation":0,"scale":1,"position":{"pointX":1451.3706930701737,"pointY":837.00502427419008},"width":482,"sublayerTransform":[1,0,0,0,0,1,0,0,0,0,1,0,0,0,0,1],"contentsRect":{"y":0,"x":0,"width":1,"height":1},"opacity":1,"edgeAntialiasingMask":251658240,"height":425,"hidden":false,"anchorPoint":{"pointX":0.5,"pointY":0.5}},"objectID":"1476BD1E-EAAC-4B8A-ACB6-1C54DE790211","layers":[{"animations":[],"layers":[],"texturedRectangle":{"isBackgroundTexture":true,"singleTextureOpacity":1,"textureType":5,"textBaseline":0,"textXHeight":0,"isVerticalText":false},"initialState":{"affineTransform":[1,0,0,1,0,0],"masksToBounds":false,"rotation":0,"scale":1,"position":{"pointX":239.62930692982627,"pointY":210.99497572580992},"width":482,"sublayerTransform":[1,0,0,0,0,1,0,0,0,0,1,0,0,0,0,1],"contentsRect":{"y":0,"x":0,"width":1,"height":1},"opacity":1,"edgeAntialiasingMask":0,"height":425,"hidden":true,"anchorPoint":{"pointX":0.5,"pointY":0.5}},"texture":"B28C276801367825A84224717157A0E8"}]}]},{"animations":[],"initialState":{"affineTransform":[1,0,0,1,0,0],"masksToBounds":false,"rotation":0,"scale":1,"position":{"pointX":960,"pointY":540},"width":1920,"sublayerTransform":[1,0,0,0,0,1,0,0,0,0,1,0,0,0,0,1],"contentsRect":{"y":0,"x":0,"width":1,"height":1},"opacity":1,"edgeAntialiasingMask":251658240,"height":1080,"hidden":false,"anchorPoint":{"pointX":0.5,"pointY":0.5}},"layers":[{"animations":[],"initialState":{"affineTransform":[1,0,0,1,0,0],"masksToBounds":false,"rotation":0,"scale":1,"position":{"pointX":1418.5749855142908,"pointY":645.4731250204552},"width":76,"sublayerTransform":[1,0,0,0,0,1,0,0,0,0,1,0,0,0,0,1],"contentsRect":{"y":0,"x":0,"width":1,"height":1},"opacity":1,"edgeAntialiasingMask":251658240,"height":341,"hidden":false,"anchorPoint":{"pointX":0.5,"pointY":0.5}},"objectID":"F287EAC6-4593-425B-B1CE-8734C4ADF207","layers":[{"animations":[],"layers":[],"texturedRectangle":{"singleTextureOpacity":1,"textXHeight":0,"shapePath":{"lineWidth":1,"flatness":0.59999999999999998,"lineCapStyle":0,"elements":[{"type":"MoveToPoint","points":[[58.408708026488739,7.4130583289691003]]},{"type":"AddLine","points":[[20.340053170897818,313.30146952349423]]}],"windingRule":0,"lineJoinStyle":0,"miterLimit":10},"isBackgroundTexture":true,"textBaseline":0,"isVerticalText":false,"textureType":5},"initialState":{"affineTransform":[1,0,0,1,0,0],"masksToBounds":false,"rotation":0,"scale":1,"position":{"pointX":36.425014485709198,"pointY":168.52687497954474},"width":76,"sublayerTransform":[1,0,0,0,0,1,0,0,0,0,1,0,0,0,0,1],"contentsRect":{"y":0,"x":0,"width":1,"height":1},"opacity":1,"edgeAntialiasingMask":0,"height":341,"hidden":true,"anchorPoint":{"pointX":0.5,"pointY":0.5}},"texture":"1C2D85C57D1BBC48B0C74B45B529F370"}]}]},{"animations":[],"initialState":{"affineTransform":[1,0,0,1,0,0],"masksToBounds":false,"rotation":0,"scale":1,"position":{"pointX":960,"pointY":540},"width":1920,"sublayerTransform":[1,0,0,0,0,1,0,0,0,0,1,0,0,0,0,1],"contentsRect":{"y":0,"x":0,"width":1,"height":1},"opacity":1,"edgeAntialiasingMask":251658240,"height":1080,"hidden":false,"anchorPoint":{"pointX":0.5,"pointY":0.5}},"layers":[{"animations":[],"initialState":{"affineTransform":[1,0,0,1,0,0],"masksToBounds":false,"rotation":0,"scale":1,"position":{"pointX":1814.8333333333335,"pointY":994.8333333333336},"width":103,"sublayerTransform":[1,0,0,0,0,1,0,0,0,0,1,0,0,0,0,1],"contentsRect":{"y":0,"x":0,"width":1,"height":1},"opacity":1,"edgeAntialiasingMask":251658240,"height":103,"hidden":false,"anchorPoint":{"pointX":0.5,"pointY":0.5}},"objectID":"6C72FF63-09FE-46FA-AECF-32DF39E1696C","layers":[{"animations":[],"layers":[],"texturedRectangle":{"singleTextureOpacity":1,"textXHeight":0,"shapePath":{"lineWidth":1,"flatness":0.59999999999999998,"lineCapStyle":0,"elements":[{"type":"MoveToPoint","points":[[37.333333333333485,67.333333333333599]]},{"type":"AddLine","points":[[37.333333333333485,101.33333333333348]]},{"type":"AddLine","points":[[101.33333333333348,51.333333333333599]]},{"type":"AddLine","points":[[37.333333333333485,1.3333333333335986]]},{"type":"AddLine","points":[[37.333333333333485,35.333333333333599]]},{"type":"AddLine","points":[[1.3333333333334849,35.333333333333599]]},{"type":"AddLine","points":[[1.3333333333334849,67.333333333333599]]},{"type":"CloseSubpath"}],"windingRule":0,"lineJoinStyle":0,"miterLimit":10},"isBackgroundTexture":true,"textBaseline":0,"isVerticalText":false,"textureType":5},"initialState":{"affineTransform":[1,0,0,1,0,0],"masksToBounds":false,"rotation":0,"scale":1,"position":{"pointX":50.166666666666515,"pointY":50.166666666666401},"width":103,"sublayerTransform":[1,0,0,0,0,1,0,0,0,0,1,0,0,0,0,1],"contentsRect":{"y":0,"x":0,"width":1,"height":1},"opacity":1,"edgeAntialiasingMask":0,"height":103,"hidden":true,"anchorPoint":{"pointX":0.5,"pointY":0.5}},"texture":"5FF86E2A824437EFAD54AE3258E09603"}]}]},{"animations":[],"initialState":{"affineTransform":[1,0,0,1,0,0],"masksToBounds":false,"rotation":0,"scale":1,"position":{"pointX":960,"pointY":540},"width":1920,"sublayerTransform":[1,0,0,0,0,1,0,0,0,0,1,0,0,0,0,1],"contentsRect":{"y":0,"x":0,"width":1,"height":1},"opacity":1,"edgeAntialiasingMask":251658240,"height":1080,"hidden":false,"anchorPoint":{"pointX":0.5,"pointY":0.5}},"layers":[{"animations":[],"initialState":{"affineTransform":[1,0,0,1,0,0],"masksToBounds":false,"rotation":0,"scale":1,"position":{"pointX":225.41771697998041,"pointY":971.99241129557299},"width":209,"sublayerTransform":[1,0,0,0,0,1,0,0,0,0,1,0,0,0,0,1],"contentsRect":{"y":0,"x":0,"width":1,"height":1},"opacity":1,"edgeAntialiasingMask":251658240,"height":90,"hidden":false,"anchorPoint":{"pointX":0.5,"pointY":0.5}},"objectID":"2DDF3F28-3408-4863-AE96-722F78A6951A","layers":[{"animations":[],"layers":[],"texturedRectangle":{"isBackgroundTexture":true,"singleTextureOpacity":1,"textureType":5,"textBaseline":0,"textXHeight":0,"isVerticalText":false},"initialState":{"affineTransform":[1,0,0,1,0,0],"masksToBounds":false,"rotation":0,"scale":1,"position":{"pointX":102.58228302001957,"pointY":43.007588704427008},"width":209,"sublayerTransform":[1,0,0,0,0,1,0,0,0,0,1,0,0,0,0,1],"contentsRect":{"y":0,"x":0,"width":1,"height":1},"opacity":1,"edgeAntialiasingMask":0,"height":90,"hidden":true,"anchorPoint":{"pointX":0.5,"pointY":0.5}},"texture":"B2F0BCA7C2A8885167BA19674E52A20A"}]}]}]}},{"effects":[{"beginTime":8.5,"baseLayer":{"animations":[],"initialState":{"affineTransform":[1,0,0,1,0,0],"masksToBounds":false,"rotation":0,"scale":1,"position":{"pointX":960,"pointY":540},"width":1920,"sublayerTransform":[1,0,0,0,0,1,0,0,0,0,1,0,0,0,0,1],"contentsRect":{"y":0,"x":0,"width":1,"height":1},"opacity":1,"edgeAntialiasingMask":251658240,"height":1080,"hidden":false,"anchorPoint":{"pointX":0.5,"pointY":0.5}},"objectID":"0","layers":[{"animations":[],"initialState":{"affineTransform":[1,0,0,1,0,0],"masksToBounds":false,"rotation":0,"scale":1,"position":{"pointX":960,"pointY":540},"width":1920,"sublayerTransform":[1,0,0,0,0,1,0,0,0,0,1,-0.00035007912466775983,0,0,0,1],"contentsRect":{"y":0,"x":0,"width":1,"height":1},"opacity":1,"edgeAntialiasingMask":251658240,"height":1080,"hidden":false,"anchorPoint":{"pointX":0.5,"pointY":0.5}},"layers":[{"animations":[{"additive":false,"timeOffset":0,"beginTime":0,"repeatCount":0,"fillMode":"both","duration":0.5,"autoreverses":false,"animations":[{"repeatCount":0,"timingControlPoint2y":1,"removedOnCompletion":true,"from":{"scalar":0.10000000000000001},"timingFunction":"custom","additive":false,"timeOffset":0,"autoreverses":false,"timingControlPoint1x":0.50116544961929321,"fillMode":"removed","property":"transform.scale.xy","duration":0.5,"beginTime":0,"timingControlPoint2x":0.59870344400405884,"timingControlPoint1y":0.79673820734024048,"to":{"scalar":1}},{"repeatCount":0,"timingControlPoint2y":1,"removedOnCompletion":true,"from":{"scalar":0},"timingFunction":"custom","additive":false,"timeOffset":0,"autoreverses":false,"timingControlPoint1x":0.50116544961929321,"fillMode":"removed","property":"opacity","duration":0.5,"beginTime":0,"timingControlPoint2x":0.59870344400405884,"timingControlPoint1y":0.79673820734024048,"to":{"scalar":1}},{"additive":false,"timeOffset":0,"beginTime":0,"from":{"scalar":0.01},"repeatCount":0,"fillMode":"removed","duration":0.5,"autoreverses":false,"property":"transform.translation.z","to":{"scalar":0.01},"removedOnCompletion":true}],"removedOnCompletion":false}],"layers":[],"texturedRectangle":{"isBackgroundTexture":false,"singleTextureOpacity":1,"textureType":0,"textBaseline":0,"textXHeight":0,"isVerticalText":false},"initialState":{"affineTransform":[1,0,0,1,0,0],"masksToBounds":false,"rotation":0,"scale":1,"position":{"pointX":960,"pointY":540},"width":1920,"sublayerTransform":[1,0,0,0,0,1,0,0,0,0,1,0,0,0,0,1],"contentsRect":{"y":0,"x":0,"width":1,"height":1},"opacity":1,"edgeAntialiasingMask":251658240,"height":1080,"hidden":false,"anchorPoint":{"pointX":0.5,"pointY":0.5}},"texture":"11A3D575BC6A00BAD4CC17A5FF6DDE99"},{"animations":[],"layers":[],"texturedRectangle":{"isBackgroundTexture":false,"singleTextureOpacity":1,"textureType":0,"textBaseline":0,"textXHeight":0,"isVerticalText":false},"initialState":{"affineTransform":[1,0,0,1,0,0],"masksToBounds":false,"rotation":0,"scale":1,"position":{"pointX":960,"pointY":540},"width":1920,"sublayerTransform":[1,0,0,0,0,1,0,0,0,0,1,0,0,0,0,1],"contentsRect":{"y":0,"x":0,"width":1,"height":1},"opacity":1,"edgeAntialiasingMask":0,"height":1080,"hidden":false,"anchorPoint":{"pointX":0.5,"pointY":0.5}},"texture":"3EDDAE3FDD7A654053D0AEA069F8D648"}]}]},"effects":[],"duration":0.5,"type":"transition","attributes":{"direction":43},"name":"apple:scale","objectID":"0"}],"automaticPlay":true,"hyperlinks":[{"url":"?slideid=8D1DB382-D47D-4A89-A9F7-6691A7196541","events":{"8D1DB382-D47D-4A89-A9F7-6691A7196541":{"effects":[{"beginTime":0,"baseLayer":{"animations":[],"initialState":{"affineTransform":[1,0,0,1,0,0],"masksToBounds":false,"rotation":0,"scale":1,"position":{"pointX":960,"pointY":540},"width":1920,"sublayerTransform":[1,0,0,0,0,1,0,0,0,0,1,0,0,0,0,1],"contentsRect":{"y":0,"x":0,"width":1,"height":1},"opacity":1,"edgeAntialiasingMask":251658240,"height":1080,"hidden":false,"anchorPoint":{"pointX":0.5,"pointY":0.5}},"objectID":"0","layers":[{"animations":[],"initialState":{"affineTransform":[1,0,0,1,0,0],"masksToBounds":false,"rotation":0,"scale":1,"position":{"pointX":960,"pointY":540},"width":1920,"sublayerTransform":[1,0,0,0,0,1,0,0,0,0,1,-0.00035007912466775983,0,0,0,1],"contentsRect":{"y":0,"x":0,"width":1,"height":1},"opacity":1,"edgeAntialiasingMask":251658240,"height":1080,"hidden":false,"anchorPoint":{"pointX":0.5,"pointY":0.5}},"layers":[{"animations":[{"additive":false,"timeOffset":0,"beginTime":0,"repeatCount":0,"fillMode":"both","duration":0.5,"autoreverses":false,"animations":[{"repeatCount":0,"timingControlPoint2y":1,"removedOnCompletion":true,"from":{"scalar":0.10000000000000001},"timingFunction":"custom","additive":false,"timeOffset":0,"autoreverses":false,"timingControlPoint1x":0.50116544961929321,"fillMode":"removed","property":"transform.scale.xy","duration":0.5,"beginTime":0,"timingControlPoint2x":0.59870344400405884,"timingControlPoint1y":0.79673820734024048,"to":{"scalar":1}},{"repeatCount":0,"timingControlPoint2y":1,"removedOnCompletion":true,"from":{"scalar":0},"timingFunction":"custom","additive":false,"timeOffset":0,"autoreverses":false,"timingControlPoint1x":0.50116544961929321,"fillMode":"removed","property":"opacity","duration":0.5,"beginTime":0,"timingControlPoint2x":0.59870344400405884,"timingControlPoint1y":0.79673820734024048,"to":{"scalar":1}},{"additive":false,"timeOffset":0,"beginTime":0,"from":{"scalar":0.01},"repeatCount":0,"fillMode":"removed","duration":0.5,"autoreverses":false,"property":"transform.translation.z","to":{"scalar":0.01},"removedOnCompletion":true}],"removedOnCompletion":false}],"layers":[],"texturedRectangle":{"isBackgroundTexture":false,"singleTextureOpacity":1,"textureType":0,"textBaseline":0,"textXHeight":0,"isVerticalText":false},"initialState":{"affineTransform":[1,0,0,1,0,0],"masksToBounds":false,"rotation":0,"scale":1,"position":{"pointX":960,"pointY":540},"width":1920,"sublayerTransform":[1,0,0,0,0,1,0,0,0,0,1,0,0,0,0,1],"contentsRect":{"y":0,"x":0,"width":1,"height":1},"opacity":1,"edgeAntialiasingMask":251658240,"height":1080,"hidden":false,"anchorPoint":{"pointX":0.5,"pointY":0.5}},"texture":"1AC1D9AB0AA6A4AF2C78CE39642C3533"},{"animations":[],"layers":[],"texturedRectangle":{"isBackgroundTexture":false,"singleTextureOpacity":1,"textureType":0,"textBaseline":0,"textXHeight":0,"isVerticalText":false},"initialState":{"affineTransform":[1,0,0,1,0,0],"masksToBounds":false,"rotation":0,"scale":1,"position":{"pointX":960,"pointY":540},"width":1920,"sublayerTransform":[1,0,0,0,0,1,0,0,0,0,1,0,0,0,0,1],"contentsRect":{"y":0,"x":0,"width":1,"height":1},"opacity":1,"edgeAntialiasingMask":0,"height":1080,"hidden":false,"anchorPoint":{"pointX":0.5,"pointY":0.5}},"texture":"3EDDAE3FDD7A654053D0AEA069F8D648"}]}]},"effects":[],"duration":0.5,"type":"transition","attributes":{"direction":43},"name":"apple:scale","objectID":"0"}],"automaticPlay":false,"hyperlinks":[],"accessibility":[],"baseLayer":{"animations":[],"initialState":{"affineTransform":[1,0,0,1,0,0],"masksToBounds":false,"rotation":0,"scale":1,"position":{"pointX":960,"pointY":540},"width":1920,"sublayerTransform":[1,0,0,0,0,1,0,0,0,0,1,0,0,0,0,1],"contentsRect":{"y":0,"x":0,"width":1,"height":1},"opacity":1,"edgeAntialiasingMask":251658240,"height":1080,"hidden":false,"anchorPoint":{"pointX":0.5,"pointY":0.5}},"objectID":"0","layers":[{"animations":[],"initialState":{"affineTransform":[1,0,0,1,0,0],"masksToBounds":false,"rotation":0,"scale":1,"position":{"pointX":960,"pointY":540},"width":1920,"sublayerTransform":[1,0,0,0,0,1,0,0,0,0,1,-0.00035007912466775983,0,0,0,1],"contentsRect":{"y":0,"x":0,"width":1,"height":1},"opacity":1,"edgeAntialiasingMask":251658240,"height":1080,"hidden":false,"anchorPoint":{"pointX":0.5,"pointY":0.5}},"layers":[{"animations":[],"layers":[],"texturedRectangle":{"isBackgroundTexture":false,"singleTextureOpacity":1,"textureType":0,"textBaseline":0,"textXHeight":0,"isVerticalText":false},"initialState":{"affineTransform":[1,0,0,1,0,0],"masksToBounds":false,"rotation":0,"scale":1,"position":{"pointX":960,"pointY":540},"width":1920,"sublayerTransform":[1,0,0,0,0,1,0,0,0,0,1,0,0,0,0,1],"contentsRect":{"y":0,"x":0,"width":1,"height":1},"opacity":1,"edgeAntialiasingMask":0,"height":1080,"hidden":false,"anchorPoint":{"pointX":0.5,"pointY":0.5}},"texture":"3EDDAE3FDD7A654053D0AEA069F8D648"}]}]}}},"targetRectangle":{"y":926.99241129557299,"x":120.91771697998043,"width":206.01460266113281,"height":86.338462829589844}},{"url":"?slideid=181B7F64-020E-4CB9-841E-548F02B0AC1D","events":{"181B7F64-020E-4CB9-841E-548F02B0AC1D":{"effects":[{"beginTime":0,"baseLayer":{"animations":[],"initialState":{"affineTransform":[1,0,0,1,0,0],"masksToBounds":false,"rotation":0,"scale":1,"position":{"pointX":960,"pointY":540},"width":1920,"sublayerTransform":[1,0,0,0,0,1,0,0,0,0,1,0,0,0,0,1],"contentsRect":{"y":0,"x":0,"width":1,"height":1},"opacity":1,"edgeAntialiasingMask":251658240,"height":1080,"hidden":false,"anchorPoint":{"pointX":0.5,"pointY":0.5}},"objectID":"0","layers":[{"animations":[],"initialState":{"affineTransform":[1,0,0,1,0,0],"masksToBounds":false,"rotation":0,"scale":1,"position":{"pointX":960,"pointY":540},"width":1920,"sublayerTransform":[1,0,0,0,0,1,0,0,0,0,1,-0.00035007912466775983,0,0,0,1],"contentsRect":{"y":0,"x":0,"width":1,"height":1},"opacity":1,"edgeAntialiasingMask":251658240,"height":1080,"hidden":false,"anchorPoint":{"pointX":0.5,"pointY":0.5}},"layers":[{"animations":[{"additive":false,"timeOffset":0,"beginTime":0,"repeatCount":0,"fillMode":"both","duration":0.5,"autoreverses":false,"animations":[{"repeatCount":0,"timingControlPoint2y":1,"removedOnCompletion":true,"from":{"scalar":0.10000000000000001},"timingFunction":"custom","additive":false,"timeOffset":0,"autoreverses":false,"timingControlPoint1x":0.50116544961929321,"fillMode":"removed","property":"transform.scale.xy","duration":0.5,"beginTime":0,"timingControlPoint2x":0.59870344400405884,"timingControlPoint1y":0.79673820734024048,"to":{"scalar":1}},{"repeatCount":0,"timingControlPoint2y":1,"removedOnCompletion":true,"from":{"scalar":0},"timingFunction":"custom","additive":false,"timeOffset":0,"autoreverses":false,"timingControlPoint1x":0.50116544961929321,"fillMode":"removed","property":"opacity","duration":0.5,"beginTime":0,"timingControlPoint2x":0.59870344400405884,"timingControlPoint1y":0.79673820734024048,"to":{"scalar":1}},{"additive":false,"timeOffset":0,"beginTime":0,"from":{"scalar":0.01},"repeatCount":0,"fillMode":"removed","duration":0.5,"autoreverses":false,"property":"transform.translation.z","to":{"scalar":0.01},"removedOnCompletion":true}],"removedOnCompletion":false}],"layers":[],"texturedRectangle":{"isBackgroundTexture":false,"singleTextureOpacity":1,"textureType":0,"textBaseline":0,"textXHeight":0,"isVerticalText":false},"initialState":{"affineTransform":[1,0,0,1,0,0],"masksToBounds":false,"rotation":0,"scale":1,"position":{"pointX":960,"pointY":540},"width":1920,"sublayerTransform":[1,0,0,0,0,1,0,0,0,0,1,0,0,0,0,1],"contentsRect":{"y":0,"x":0,"width":1,"height":1},"opacity":1,"edgeAntialiasingMask":251658240,"height":1080,"hidden":false,"anchorPoint":{"pointX":0.5,"pointY":0.5}},"texture":"11A3D575BC6A00BAD4CC17A5FF6DDE99"},{"animations":[],"layers":[],"texturedRectangle":{"isBackgroundTexture":false,"singleTextureOpacity":1,"textureType":0,"textBaseline":0,"textXHeight":0,"isVerticalText":false},"initialState":{"affineTransform":[1,0,0,1,0,0],"masksToBounds":false,"rotation":0,"scale":1,"position":{"pointX":960,"pointY":540},"width":1920,"sublayerTransform":[1,0,0,0,0,1,0,0,0,0,1,0,0,0,0,1],"contentsRect":{"y":0,"x":0,"width":1,"height":1},"opacity":1,"edgeAntialiasingMask":0,"height":1080,"hidden":false,"anchorPoint":{"pointX":0.5,"pointY":0.5}},"texture":"3EDDAE3FDD7A654053D0AEA069F8D648"}]}]},"effects":[],"duration":0.5,"type":"transition","attributes":{"direction":43},"name":"apple:scale","objectID":"0"}],"automaticPlay":false,"hyperlinks":[],"accessibility":[],"baseLayer":{"animations":[],"initialState":{"affineTransform":[1,0,0,1,0,0],"masksToBounds":false,"rotation":0,"scale":1,"position":{"pointX":960,"pointY":540},"width":1920,"sublayerTransform":[1,0,0,0,0,1,0,0,0,0,1,0,0,0,0,1],"contentsRect":{"y":0,"x":0,"width":1,"height":1},"opacity":1,"edgeAntialiasingMask":251658240,"height":1080,"hidden":false,"anchorPoint":{"pointX":0.5,"pointY":0.5}},"objectID":"0","layers":[{"animations":[],"initialState":{"affineTransform":[1,0,0,1,0,0],"masksToBounds":false,"rotation":0,"scale":1,"position":{"pointX":960,"pointY":540},"width":1920,"sublayerTransform":[1,0,0,0,0,1,0,0,0,0,1,-0.00035007912466775983,0,0,0,1],"contentsRect":{"y":0,"x":0,"width":1,"height":1},"opacity":1,"edgeAntialiasingMask":251658240,"height":1080,"hidden":false,"anchorPoint":{"pointX":0.5,"pointY":0.5}},"layers":[{"animations":[],"layers":[],"texturedRectangle":{"isBackgroundTexture":false,"singleTextureOpacity":1,"textureType":0,"textBaseline":0,"textXHeight":0,"isVerticalText":false},"initialState":{"affineTransform":[1,0,0,1,0,0],"masksToBounds":false,"rotation":0,"scale":1,"position":{"pointX":960,"pointY":540},"width":1920,"sublayerTransform":[1,0,0,0,0,1,0,0,0,0,1,0,0,0,0,1],"contentsRect":{"y":0,"x":0,"width":1,"height":1},"opacity":1,"edgeAntialiasingMask":0,"height":1080,"hidden":false,"anchorPoint":{"pointX":0.5,"pointY":0.5}},"texture":"3EDDAE3FDD7A654053D0AEA069F8D648"}]}]}}},"targetRectangle":{"y":943.3333333333336,"x":1763.3333333333335,"width":100,"height":99.999999999999886}}],"accessibility":[{"text":"Africa_satellite_orthographic.jpg","targetRectangle":{"y":258.29998811086011,"x":502.65523258845002,"width":682.6895751953125,"height":766.7646484375}},{"text":"Vamos a Egipto","targetRectangle":{"y":10.999996344248459,"x":377.51203266779544,"width":932.97599999999989,"height":170}},{"text":"vídeo-pegado.png","targetRectangle":{"y":-5.671875,"x":-4.4353184700012207,"width":2165.380126953125,"height":1091.34375}},{"text":"16974495410320-2023-10-16-19-59-19.jpeg","targetRectangle":{"y":375.23419122995927,"x":511.75861183802266,"width":140.13401892719781,"height":68.125}},{"text":"historia_0021_2.jpg","targetRectangle":{"y":378.08380315701174,"x":904.37495772043894,"width":111.25008392333984,"height":40.977115631103516}},{"text":"Volver","targetRectangle":{"y":942.33365766207385,"x":158.09701538085932,"width":130.65600000000001,"height":55.656005859375}},{"text":"Mapa_político_da_África.svg.png","targetRectangle":{"y":624.50502427419008,"x":1210.3706930701737,"width":479.53497476814209,"height":421.79173350334156}}],"baseLayer":{"animations":[],"initialState":{"affineTransform":[1,0,0,1,0,0],"masksToBounds":false,"rotation":0,"scale":1,"position":{"pointX":960,"pointY":540},"width":1920,"sublayerTransform":[1,0,0,0,0,1,0,0,0,0,1,0,0,0,0,1],"contentsRect":{"y":0,"x":0,"width":1,"height":1},"opacity":1,"edgeAntialiasingMask":251658240,"height":1080,"hidden":false,"anchorPoint":{"pointX":0.5,"pointY":0.5}},"objectID":"0","layers":[{"animations":[],"initialState":{"affineTransform":[1,0,0,1,0,0],"masksToBounds":false,"rotation":0,"scale":1,"position":{"pointX":960,"pointY":540},"width":1920,"sublayerTransform":[1,0,0,0,0,1,0,0,0,0,1,-0.00035007912466775983,0,0,0,1],"contentsRect":{"y":0,"x":0,"width":1,"height":1},"opacity":1,"edgeAntialiasingMask":251658240,"height":1080,"hidden":false,"anchorPoint":{"pointX":0.5,"pointY":0.5}},"layers":[{"animations":[],"layers":[],"texturedRectangle":{"isBackgroundTexture":false,"singleTextureOpacity":1,"textureType":0,"textBaseline":0,"textXHeight":0,"isVerticalText":false},"initialState":{"affineTransform":[1,0,0,1,0,0],"masksToBounds":false,"rotation":0,"scale":1,"position":{"pointX":960,"pointY":540},"width":1920,"sublayerTransform":[1,0,0,0,0,1,0,0,0,0,1,0,0,0,0,1],"contentsRect":{"y":0,"x":0,"width":1,"height":1},"opacity":1,"edgeAntialiasingMask":0,"height":1080,"hidden":false,"anchorPoint":{"pointX":0.5,"pointY":0.5}},"texture":"3EDDAE3FDD7A654053D0AEA069F8D648"}]}]}}]}